{
  "inlineCSS": true,
  "inlineJS": true,
  "inlineImages": true,
  "includePluginCSS": "",
  "includeSvelteCSS": true,
  "makeNamesWebStyle": false,
  "allowFoldingHeadings": true,
  "sidebarsAlwaysCollapsible": false,
  "addFilenameTitle": true,
  "minifyHTML": true,
  "customLineWidth": "",
  "contentWidth": "",
  "sidebarWidth": "",
  "startOutlineCollapsed": false,
  "logLevel": "warning",
  "incrementalExport": false,
  "deleteOldExportedFiles": false,
  "addDarkModeToggle": true,
  "includeOutline": true,
  "includeGraphView": false,
  "includeFileTree": true,
  "exportPreset": "documents",
  "openAfterExport": true,
  "graphAttractionForce": 1,
  "graphLinkLength": 10,
  "graphRepulsionForce": 150,
  "graphCentralForce": 3,
  "graphEdgePruning": 100,
  "graphMinNodeSize": 3,
  "graphMaxNodeSize": 7,
  "exportPath": "/home/relli/Desktop/competitive-programming",
  "filesToExport": [
    [
      "imgs/IMG_0394.png",
      "imgs/Pasted image 20240105111518.png",
      "imgs/Screenshot from 2024-01-05 09-23-27.png",
      "imgs/Screenshot from 2024-01-05 09-29-59.png",
      "imgs/Screenshot from 2024-01-05 10-26-37.png",
      "imgs/Screenshot from 2024-01-05 11-17-40.png",
      "cp-notes.md"
    ]
  ]
}